litestar_geoalchemy/__init__.py
litestar_geoalchemy/openapi.py
litestar_geoalchemy/plugin.py
litestar_geoalchemy/py.typed
litestar_geoalchemy/types.py
litestar_geoalchemy-0.2.1.dist-info/WHEEL
litestar_geoalchemy-0.2.1.dist-info/METADATA
litestar_geoalchemy-0.2.1.dist-info/RECORD
