Metadata-Version: 2.4
Name: litestar-geoalchemy
Version: 0.2.1
Summary: Litestar plugin for GeoAlchemy2 - seamless GeoJSON serialization with PostGIS
Keywords: litestar,geoalchemy2,geojson,postgis,gis,spatial
Author: cemrehancavdar
Author-email: cemrehancavdar <cemrehandev@gmail.com>
License-Expression: MIT
Classifier: Development Status :: 4 - Beta
Classifier: Intended Audience :: Developers
Classifier: License :: OSI Approved :: MIT License
Classifier: Programming Language :: Python :: 3
Classifier: Programming Language :: Python :: 3.10
Classifier: Programming Language :: Python :: 3.11
Classifier: Programming Language :: Python :: 3.12
Classifier: Programming Language :: Python :: 3.13
Classifier: Topic :: Database
Classifier: Topic :: Scientific/Engineering :: GIS
Requires-Dist: geoalchemy2>=0.16.0
Requires-Dist: litestar>=2.0
Requires-Dist: shapely>=2.0.0
Requires-Python: >=3.10
